specArt/__init__.py
specArt/specArt.py
specart-0.0.1.dist-info/METADATA
specart-0.0.1.dist-info/WHEEL
specart-0.0.1.dist-info/licenses/LICENSE.txt
specart-0.0.1.dist-info/RECORD
