Metadata-Version: 2.4
Name: specArt
Version: 0.0.1
Summary: specArt: Convert images into spectrum art ready to be broadcast on your favourite frequency.
Project-URL: Homepage, https://github.com/importThat/specArt
Project-URL: Source, https://github.com/importThat/specArt
Author: importThat
License: MIT License
License-File: LICENSE.txt
Keywords: art,dsp,radio,sdr,signal,spectrum,wave
Classifier: Programming Language :: Python
Classifier: Programming Language :: Python :: 3.12
Classifier: Programming Language :: Python :: 3.13
Classifier: Programming Language :: Python :: Implementation :: CPython
Requires-Python: >=3.12
Requires-Dist: numpy
Requires-Dist: pillow
